[
	{
		"Author": "XiYu",
		"Name": "JobAssist",
		"Description": "A plugin to do something that you always forget",
		"InternalName": "JobAssist",
		"AssemblyVersion": "2.0.0.6",
		"RepoUrl": "",
		"ApplicableVersion": "any",
		"Tags": [
			"Ninjutsu",
			"Assist",
			"Xiyu"
		],
		"DalamudApiLevel": 5,
		"Testing": false,
		"InstalledFromUrl": null,
		"Punchline": "Job Assist",
		"DownloadLinkInstall": "https://github.com/Karlin-Z/DalamudPlugins/raw/Api4/plugins/JobAssist/latest.zip",
		"IsHide": false,
		"IsTestingExclusive": false,
		"DownloadLinkTesting": "https://github.com/Karlin-Z/DalamudPlugins/raw/Api4/plugins/JobAssist/latest.zip",
		"DownloadLinkUpdate": "https://github.com/Karlin-Z/DalamudPlugins/raw/Api4/plugins/JobAssist/latest.zip",
		"DownloadCount": 0,
		"LastUpdated": "1618843696"
	},
	{
		"Author": "Sevii",
		"Name": "Material UI",
		"Description": "Auto updating Material UI with customizable accent color and more. Icon by Meconate",
		"InternalName": "MaterialUI",
		"AssemblyVersion": "1.4.7",
		"TestingAssemblyVersion": "1.4.7",
		"RepoUrl": "https://github.com/Sevii77/ffxiv_materialui_accent",
		"ApplicableVersion": "any",
		"DalamudApiLevel": 6,
		"IsHide": "False",
		"IsTestingExclusive": "False",
		"DownloadCount": 0,
		"LastUpdate": 0,
		"DownloadLinkInstall": "https://github.com/Sevii77/ffxiv_materialui_accent/raw/master/release.zip",
		"DownloadLinkTesting": "https://github.com/Sevii77/ffxiv_materialui_accent/raw/master/release.zip",
		"DownloadLinkUpdate": "https://github.com/Sevii77/ffxiv_materialui_accent/raw/master/release.zip",
		"IconUrl": "https://raw.githubusercontent.com/Sevii77/ffxiv_materialui_accent/master/images/icon.png",
		"Tags": [
			"ui",
			"penumbra",
			"material",
			"skotlex",
			"sevii",
			"accent",
			"color"
		]
	},
	{
		"Author": "",
		"Name": "Lock",
		"Punchline": "\u9501\u5b9a",
		"Description": "\u9501\u5b9aBOSS /LockBOSS change 1 \u9760\u8fd1\u6c34\u6676\u5207\u63621\u53f7\u7ebf\u8def\n/LockBOSS qi\u9a91\u4e0a\u6700\u8fd1\u7684\u4eba\n/LockBOSS cai\u91c7\u96c6\u6700\u8fd1\u7684\u77ff,",
		"InternalName": "Lock",
		"AssemblyVersion": "1.0.1.5",
		"RepoUrl": "",
		"ApplicableVersion": "any",
		"DalamudApiLevel": 7,
		"IconUrl": "https://github.com/tssailzz8/MyPlugins/raw/master/plugins/Lock/2-%E5%9B%BE%E7%89%87.png",
		"ImageUrls": [],
		"DownloadLinkInstall": "https://github.com/tssailzz8/MyPlugins/raw/master/plugins/Lock/latest.zip",
		"IsHide": false,
		"IsTestingExclusive": false,
		"DownloadLinkTesting": "https://github.com/tssailzz8/MyPlugins/raw/master/plugins/Lock/latest.zip",
		"DownloadLinkUpdate": "https://github.com/tssailzz8/MyPlugins/raw/master/plugins/Lock/latest.zip",
		"DownloadCount": 0,
		"LastUpdated": "1660131872"
	},
	{
		"Author": "UnknownX",
		"Name": "NoClippy",
		"Punchline": "Reduces the effects of lag on certain aspects of the game, and can show GCD clips",
		"Description": "Reduces the effects of lag on certain aspects of the game, such as weaving and statuses. Usable as an alternative, or in addition, to XivAlexander.",
		"Changelog": "",
		"InternalName": "NoClippy",
		"AssemblyVersion": "0.4.0.9",
		"RepoUrl": "https://github.com/UnknownX7/NoClippy",
		"ApplicableVersion": "any",
		"CategoryTags": [
			"jobs",
			"utility"
		],
		"DalamudApiLevel": 6,
		"IconUrl": "",
		"ImageUrls": [
			""
		],
		"DownloadLinkInstall": "https://github.com/UnknownX7/DalamudPluginRepo/raw/master/plugins/NoClippy/latest.zip",
		"IsHide": false,
		"IsTestingExclusive": false,
		"DownloadLinkTesting": "https://github.com/UnknownX7/DalamudPluginRepo/raw/master/plugins/NoClippy/latest.zip",
		"DownloadLinkUpdate": "https://github.com/UnknownX7/DalamudPluginRepo/raw/master/plugins/NoClippy/latest.zip",
		"DownloadCount": 0,
		"LastUpdate": "1653186885"
	},
	{
		"Author": "UnknownX",
		"Name": "Fractionality",
		"Punchline": "Changes /wait and <wait> to support fractions",
		"Description": "Adds 3 decimal precision waiting to macros and removes the 60 seconds cap.",
		"Changelog": "",
		"InternalName": "Fractionality",
		"AssemblyVersion": "1.0.1.2",
		"RepoUrl": "https://github.com/UnknownX7/Fractionality",
		"ApplicableVersion": "any",
		"DalamudApiLevel": 6,
		"IconUrl": "",
		"ImageUrls": [
			""
		],
		"DownloadLinkInstall": "https://github.com/UnknownX7/DalamudPluginRepo/raw/master/plugins/Fractionality/latest.zip",
		"IsHide": false,
		"IsTestingExclusive": false,
		"DownloadLinkTesting": "https://github.com/UnknownX7/DalamudPluginRepo/raw/master/plugins/Fractionality/latest.zip",
		"DownloadLinkUpdate": "https://github.com/UnknownX7/DalamudPluginRepo/raw/master/plugins/Fractionality/latest.zip",
		"DownloadCount": 0,
		"LastUpdate": "1653186885"
	},
	{
		"Author": "XiYu",
		"Name": "Gold Saucer Assist",
		"Description": "A plugin for Gold Saucer",
		"InternalName": "GoldSaucerAssist",
		"AssemblyVersion": "2.1.0.0",
		"RepoUrl": "",
		"ApplicableVersion": "any",
		"Tags": [
			"Gold Saucer",
			"Slice is Right",
			"Xiyu"
		],
		"DalamudApiLevel": 5,
		"Testing": false,
		"InstalledFromUrl": null,
		"Punchline": "Gold Saucer",
		"DownloadLinkInstall": "https://github.com/Karlin-Z/DalamudPlugins/raw/Api4/plugins/GoldSaucerAssist/latest.zip",
		"IsHide": false,
		"IsTestingExclusive": false,
		"DownloadLinkTesting": "https://github.com/Karlin-Z/DalamudPlugins/raw/Api4/plugins/GoldSaucerAssist/latest.zip",
		"DownloadLinkUpdate": "https://github.com/Karlin-Z/DalamudPlugins/raw/Api4/plugins/GoldSaucerAssist/latest.zip",
		"DownloadCount": 0,
		"LastUpdated": "1618843696"
	},
	{
		"Author": "akira0245",
		"Name": "MidiBard",
		"Punchline": "Bard performance using midi files or keyboard.",
		"Description": "\u4f7f\u7528MIDI\u6587\u4ef6\u6216MIDI\u952e\u76d8\u8fdb\u884c\u8bd7\u4eba\u6f14\u594f\u3002\nBard performance using midi files or keyboard.\n- Solo and ensemble mode support\n- Text commands for instrument equip and switch",
		"InternalName": "MidiBard",
		"AssemblyVersion": "1.10.1.1",
		"RepoUrl": "https://github.com/akira0245/MidiBard",
		"ApplicableVersion": "any",
		"Tags": [
			"akira",
			"perform",
			"instrument"
		],
		"CategoryTags": [
			"utility",
			"other"
		],
		"DalamudApiLevel": 6,
		"IconUrl": "https://i.loli.net/2021/09/09/L1fkrwElUKYMtN3.png",
		"DownloadLinkInstall": "https://github.com/akira0245/DalamudPlugins/raw/api4/plugins/MidiBard/latest.zip",
		"IsHide": false,
		"IsTestingExclusive": false,
		"DownloadLinkTesting": "https://github.com/akira0245/DalamudPlugins/raw/api4/plugins/MidiBard/latest.zip",
		"DownloadLinkUpdate": "https://github.com/akira0245/DalamudPlugins/raw/api4/plugins/MidiBard/latest.zip",
		"DownloadCount": 0,
		"LastUpdated": "1657737239"
	},
	{
		"Author": "daemitus",
		"Name": "Yes Already",
		"Punchline": "Clicks Yes in various dialogs you've specified.",
		"Description": "Tired of clicking yes in Praetorium? Can't stand using keys in dungeons? Well do I have the plugin for you! Yes Already is specifically designed to click all the annoying dialogs you've grown accustomed facerolling. Just enter the dialog text, and you'll never see it again! Also works with /regex/ and has several built-in modules for dialogs that aren't quite yes/no prompts but act like it (like desynth).",
		"InternalName": "YesAlready",
		"AssemblyVersion": "1.2.2.1",
		"RepoUrl": "https://github.com/daemitus/YesAlready",
		"ApplicableVersion": "any",
		"DalamudApiLevel": 6,
		"LoadPriority": 1,
		"IconUrl": "https://github.com/daemitus/YesAlready/raw/master/res/icon.png",
		"ImageUrls": [],
		"DownloadLinkInstall": "https://github.com/daemitus/MyDalamudPlugins/raw/master/plugins/YesAlready/latest.zip",
		"IsHide": false,
		"IsTestingExclusive": false,
		"DownloadLinkTesting": "https://github.com/daemitus/MyDalamudPlugins/raw/master/plugins/YesAlready/latest.zip",
		"DownloadLinkUpdate": "https://github.com/daemitus/MyDalamudPlugins/raw/master/plugins/YesAlready/latest.zip",
		"DownloadCount": 0,
		"LastUpdate": "1659304020"
	},
	{
		"Author": "Eternita",
		"Name": "AntiAfkKick",
		"Punchline": "A Dalamud plugin for preventing being auto-kicked from FFXIV due to inactivity. Install and forget, no config needed.",
		"Description": "",
		"InternalName": "AntiAfkKick-Dalamud",
		"AssemblyVersion": "2.1.0.1",
		"RepoUrl": "https://github.com/Eternita-S/AntiAfkKick",
		"ApplicableVersion": "any",
		"DalamudApiLevel": 6,
		"IconUrl": "",
		"ImageUrls": [],
		"DownloadLinkInstall": "https://github.com/Eternita-S/MyDalamudPlugins/releases/download/Latest/AntiAfkKick.zip",
		"IsHide": false,
		"IsTestingExclusive": false,
		"DownloadLinkTesting": "https://github.com/Eternita-S/MyDalamudPlugins/releases/download/Latest/AntiAfkKick.zip",
		"DownloadLinkUpdate": "https://github.com/Eternita-S/MyDalamudPlugins/releases/download/Latest/AntiAfkKick.zip",
		"DownloadCount": 0,
		"LastUpdated": "0"
	},
	{
		"Author": "Eternita",
		"Name": "Prioritizer",
		"Punchline": "Prioritizer sets game's priority to high while crafting. No more failed crafts due to random lags while game is minimized.",
		"InternalName": "Prioritizer",
		"AssemblyVersion": "2.0.0.3",
		"RepoUrl": "https://github.com/Eternita-S/Prioritizer",
		"ApplicableVersion": "any",
		"DalamudApiLevel": 6,
		"IconUrl": "",
		"ImageUrls": [],
		"DownloadLinkInstall": "https://github.com/Eternita-S/MyDalamudPlugins/releases/download/Latest/Prioritizer.zip",
		"IsHide": false,
		"IsTestingExclusive": false,
		"DownloadLinkTesting": "https://github.com/Eternita-S/MyDalamudPlugins/releases/download/Latest/Prioritizer.zip",
		"DownloadLinkUpdate": "https://github.com/Eternita-S/MyDalamudPlugins/releases/download/Latest/Prioritizer.zip",
		"DownloadCount": 0,
		"LastUpdated": "0"
	}
]